[
    {
        "metainfo_file": {
            "_id": "6756f6d858182dcc25a1df98",
            "createBy": "quang-trung",
            "info": {
                "length": 33868,
                "name": "util.py",
                "piece_length": 33868,
                "pieces": "TjqsBuaiG2eo8U537jUQ+NTtK6w="
            },
            "info_hash": "b0001bf9a88c5b978a9d8370fd51d619c588ca5e"
        },
        "file_path": "./repo/util.py.part",
        "peer_id": "080ebdb8-5c42-4da4-9bcd-7c3b24d9c894",
        "info_hash": "b0001bf9a88c5b978a9d8370fd51d619c588ca5e",
        "uploaded": 0,
        "downloaded": 33868,
        "left": 0,
        "event": "completed",
        "pieces": [
            {
                "piece_index": 0,
                "isDownloaded": true,
                "done_block": 3,
                "blocks": [
                    {
                        "offset": 0,
                        "block_size": 16384,
                        "isDownloaded": true,
                        "block_index": 0
                    },
                    {
                        "offset": 16384,
                        "block_size": 16384,
                        "isDownloaded": true,
                        "block_index": 1
                    },
                    {
                        "offset": 32768,
                        "block_size": 1100,
                        "isDownloaded": true,
                        "block_index": 2
                    }
                ]
            }
        ]
    }
]